gridhandle/__init__.py
gridhandle/gridhandle.py
qtgrid/__init__.py
qtgrid/qtgrid.py
qtgrid-1.0.0.dist-info/LICENSE
qtgrid-1.0.0.dist-info/METADATA
qtgrid-1.0.0.dist-info/WHEEL
qtgrid-1.0.0.dist-info/top_level.txt
qtgrid-1.0.0.dist-info/RECORD
