Metadata-Version: 2.1
Name: qtgrid
Version: 1.0.0
Summary: Make working with QGridLayout easier
Home-page: https://devlog42.github.io/qtgrid/
Author: Detlef von der Hülst
Author-email: devlog@gmx.de
License: UNKNOWN
Project-URL: Tutorial, https://devlog42.github.io/qtgrid/tutorial/
Project-URL: Reference Manual, https://devlog42.github.io/qtgrid/reference/
Project-URL: API Documentation, https://devlog42.github.io/qtgrid/api/
Project-URL: Bug Reports, https://github.com/devlog42/qtgrid/issues
Project-URL: Source, https://github.com/devlog42/qtgrid
Keywords: PyQt5 PyQt6 PySide6 QGridLayout
Platform: UNKNOWN
Classifier: Development Status :: 4 - Beta
Classifier: Intended Audience :: Developers
Classifier: Topic :: Software Development :: Build Tools
Classifier: Operating System :: OS Independent
Classifier: License :: OSI Approved :: GNU Lesser General Public License v3 (LGPLv3)
Classifier: Programming Language :: Python :: 3.7
Classifier: Programming Language :: Python :: 3.8
Classifier: Programming Language :: Python :: 3.9
Requires-Python: >=3.7.*, <4
License-File: LICENSE
Provides-Extra: dev
